{
  "scale": 101.60000000000001,
  "paths": [
    [
      {
        "x": 660.40625,
        "y": 101
      },
      {
        "x": 660.40625,
        "y": 100
      },
      {
        "x": 663.40625,
        "y": 97
      },
      {
        "x": 667.40625,
        "y": 94
      },
      {
        "x": 673.40625,
        "y": 90
      },
      {
        "x": 682.40625,
        "y": 86
      },
      {
        "x": 692.40625,
        "y": 82
      },
      {
        "x": 706.40625,
        "y": 78
      },
      {
        "x": 721.40625,
        "y": 74
      },
      {
        "x": 736.40625,
        "y": 72
      },
      {
        "x": 750.40625,
        "y": 71
      },
      {
        "x": 763.40625,
        "y": 71
      },
      {
        "x": 776.40625,
        "y": 72
      },
      {
        "x": 790.40625,
        "y": 76
      },
      {
        "x": 801.40625,
        "y": 82
      },
      {
        "x": 811.40625,
        "y": 89
      },
      {
        "x": 810.40625,
        "y": 121
      },
      {
        "x": 797.40625,
        "y": 120
      },
      {
        "x": 782.40625,
        "y": 118
      },
      {
        "x": 764.40625,
        "y": 114
      },
      {
        "x": 745.40625,
        "y": 107
      },
      {
        "x": 730.40625,
        "y": 101
      },
      {
        "x": 720.40625,
        "y": 96
      },
      {
        "x": 715.40625,
        "y": 92
      },
      {
        "x": 713.40625,
        "y": 89
      },
      {
        "x": 713.40625,
        "y": 87
      },
      {
        "x": 714.40625,
        "y": 83
      },
      {
        "x": 716.40625,
        "y": 80
      },
      {
        "x": 721.40625,
        "y": 77
      },
      {
        "x": 730.40625,
        "y": 73
      },
      {
        "x": 742.40625,
        "y": 71
      },
      {
        "x": 755.40625,
        "y": 70
      },
      {
        "x": 771.40625,
        "y": 71
      },
      {
        "x": 787.40625,
        "y": 74
      },
      {
        "x": 804.40625,
        "y": 77
      },
      {
        "x": 802.40625,
        "y": 119
      },
      {
        "x": 782.40625,
        "y": 121
      },
      {
        "x": 760.40625,
        "y": 121
      },
      {
        "x": 738.40625,
        "y": 118
      },
      {
        "x": 714.40625,
        "y": 115
      },
      {
        "x": 694.40625,
        "y": 112
      },
      {
        "x": 680.40625,
        "y": 107
      },
      {
        "x": 673.40625,
        "y": 105
      },
      {
        "x": 670.40625,
        "y": 102
      },
      {
        "x": 670.40625,
        "y": 101
      },
      {
        "x": 671.40625,
        "y": 99
      },
      {
        "x": 675.40625,
        "y": 95
      },
      {
        "x": 683.40625,
        "y": 88
      },
      {
        "x": 695.40625,
        "y": 80
      },
      {
        "x": 709.40625,
        "y": 73
      },
      {
        "x": 724.40625,
        "y": 66
      },
      {
        "x": 740.40625,
        "y": 61
      },
      {
        "x": 756.40625,
        "y": 58
      },
      {
        "x": 772.40625,
        "y": 56
      },
      {
        "x": 787.40625,
        "y": 56
      },
      {
        "x": 799.40625,
        "y": 57
      },
      {
        "x": 808.40625,
        "y": 60
      },
      {
        "x": 810.40625,
        "y": 82
      },
      {
        "x": 802.40625,
        "y": 84
      },
      {
        "x": 792.40625,
        "y": 86
      },
      {
        "x": 780.40625,
        "y": 87
      },
      {
        "x": 764.40625,
        "y": 87
      },
      {
        "x": 749.40625,
        "y": 86
      },
      {
        "x": 735.40625,
        "y": 84
      },
      {
        "x": 725.40625,
        "y": 82
      },
      {
        "x": 719.40625,
        "y": 82
      },
      {
        "x": 717.40625,
        "y": 81
      },
      {
        "x": 716.40625,
        "y": 81
      },
      {
        "x": 716.40625,
        "y": 80
      },
      {
        "x": 716.40625,
        "y": 78
      },
      {
        "x": 717.40625,
        "y": 76
      },
      {
        "x": 722.40625,
        "y": 72
      },
      {
        "x": 728.40625,
        "y": 67
      },
      {
        "x": 736.40625,
        "y": 62
      },
      {
        "x": 746.40625,
        "y": 58
      },
      {
        "x": 757.40625,
        "y": 55
      },
      {
        "x": 769.40625,
        "y": 53
      },
      {
        "x": 783.40625,
        "y": 52
      },
      {
        "x": 794.40625,
        "y": 53
      },
      {
        "x": 804.40625,
        "y": 55
      },
      {
        "x": 811.40625,
        "y": 58
      },
      {
        "x": 809.40625,
        "y": 74
      },
      {
        "x": 802.40625,
        "y": 77
      },
      {
        "x": 793.40625,
        "y": 79
      },
      {
        "x": 783.40625,
        "y": 82
      },
      {
        "x": 772.40625,
        "y": 84
      },
      {
        "x": 761.40625,
        "y": 85
      },
      {
        "x": 747.40625,
        "y": 86
      },
      {
        "x": 734.40625,
        "y": 86
      },
      {
        "x": 720.40625,
        "y": 85
      }
    ]
  ],
  "info": {
    "userId": "b0tScycF0q",
    "name": "b0tScycF0q",
    "ip": "::1",
    "uag": "Mozilla/5.0 (Macintosh; Intel Mac OS X 10_15_5) AppleWebKit/537.36 (KHTML, like Gecko) Chrome/85.0.4183.102 Safari/537.36 Edg/85.0.564.51",
    "inTime": 1600420527121,
    "writeTime": 1600420548987,
    "outTime": null
  }
}